axilivologger/__init__.py
axilivologger/logger.py
axilivologger-0.0.0.dist-info/METADATA
axilivologger-0.0.0.dist-info/WHEEL
axilivologger-0.0.0.dist-info/top_level.txt
axilivologger-0.0.0.dist-info/RECORD
