Metadata-Version: 2.4
Name: axilivologger
Version: 0.0.0
Summary: This is a simple logger package
Author: Ram Pareek
Author-email: ram.pareek@gmail.com
Dynamic: author
Dynamic: author-email
Dynamic: summary
